     
{
  "@graph": [

    
    {

      "@context":  
        { 
        "vocab": "http://schema.org/",
        "study": "https://covid19.ohdsi.app/study/",
            "owl": "http://www.w3.org/2002/07/owl#",
            "person": "https://covid19.ohdsi.app/author/",
            "snomed": "http://snomed.info/id/",
            "concept": "http://data.ohdsi.org/concept/",
            "xsd": "http://www.w3.org/2001/XMLSchema#",
            "ohdsi": "http://data.ohdsi.org/",
            "covid19": "https://covid19.ohdsi.app/", 
            "aphrc": "https://aphrc.org/"
        },

      "@id": "dataset:coordinatingcenterCDM",
      "@type": "schema:Dataset",
      "identifier": "<nil>",
      "name": "Coordinating Center OMOP CDM",
      "spatialCoverage": {
         "@type": "schema:Place",
         "geo": {
             "@type": "schema:GeoShape",
             "polygon": "<nil>"
         }
      },
      "temporalCoverage": "<nil>",
      "ohdsi:investigator": [
        "person:MuyingoS"
      ],
      "ohdsi:institution": {
          "@type": "schema:Organization",
          "identifier": "<nil>",
          "name": "Mumbas"
      },
      "hasPart": [
          "dataset:ConditionOccurrence",
          "dataset:Person"
      ]
    },
    {
      "@id": "creativework:IDSRproject", 
      "@type": "schema:CreativeWork",
      "author": [
        "person:MuyingoS", 
        "person:TaylorA"
      ],
      "discussionUrl": "<nil>", 
      "publication": "<nil>",
      "dateCreated": "2023-03-26"
    },
    {
      "@id": "dataset:mubasCDM",
      "@type": "schema:Dataset",
      "identifier": "<nil>",
      "name": "Malawi/MUBAS OMOP CDM",
      "version": "5.4",
      "keywords": ["OMOP CDM", "COVID-19", "SARS-CoV-2", "Transmission", "Surveillance","Symptoms","Diagnosis", "Treatment", "Response", "Vaccine","Specimen"],
      "spatialCoverage": {
         "@type": "schema:Place",
         "geo": {
             "@type": "schema:GeoShape",
             "polygon": "<nil>"
         }
      },
      "temporalCoverage": "<nil>",
      "ohdsi:investigator": [
        "person:TaylorA"
      ],
      "ohdsi:institution": {
          "@type": "schema:Organization",
          "identifier": "<nil>",
          "name": "Mubas"
      },
      "hasPart": [
        {
            "@type": "schema:Dataset",
            "name": "OMOP CDM Person table",
            "description": "OMOP CDM Person table for Malawi IDSR data",            
            "variableMeasured": [
              {
                "@type": "PropertyValue",
                "name": "person id",
                "alternateName":"none",
                "description": "Unique person identifier",
                "value": "number",
                "minValue": "1",
                "maxValue": "51299"
              },
              {
                "@type": "PropertyValue",
                "name": "gender concept id",
                "propertyID": [
                    "https://athena.ohdsi.org/search-terms/terms/8532",
                    "https://athena.ohdsi.org/search-terms/terms/8507"
                ],
                "sameAs": [
                    "http://snomed.info/id/139867007",
                    "http://snomed.info/id/248153007"
                ],
                "alternateName": "none",
                "description": "Gender Concept ID (FEMALE=8532, MALE=8507)",
                "value": "number"
              },
              {
                "@type": "PropertyValue",
                "name": "gender_source_concept_id",
                "propertyID": [
                    "F",
                    "M"
                ],
                "subjectOf": {
                    "@type": "schema:CreativeWork",
                    "name": "WHO IDSR Africa",
                    "description": "Techncal Guidelines for Integrated Disease Surveillance and Response in the WHO African Region",
                    "url": "https://apps.who.int/iris/bitstream/handle/10665/312317/WHO-AF-WHE-CPI-01-2019-eng.pdf",
                    "hasPart": {
                        "@type": "schema:CreativeWork",
                        "name": "Annex 2F",
                        "description": "IDSR immediate case-based reporting form."
                    }
                    
                },
                "alternateName": "none",
                "description": "Gender Concept ID (FEMALE=8532, MALE=8507)",
                "value": "number"
              },
              {
                "@type": "PropertyValue",
                "name": "year of birth",
                "alternateName": "none",
                "description": "year of birth",
                "value": "number"
              }
            ]
        },
        {
            "@type": "schema:Dataset",
            "name": "OMOP CDM observation table",
            "description": "OMOP CDM observation table for Malawi IDSR data"
        },
        {
            "@type": "schema:Dataset",
            "name": "specimen",
            "description": "OMOP CDM specimen table for Malawi IDSR data"
        },
        {
            "@type": "schema:Dataset",
            "name": "visit_occurrence",
            "description": "OMOP CDM visit occurrence table for Malawi IDSR data"
        },
        {
            "@type": "schema:Dataset",
            "name": "care_site",
            "description": "OMOP CDM care site table for Malawi IDSR data"
        },
        {
            "@type": "schema:Dataset",
            "name": "condition_occurrence",
            "description": "OMOP CDM condition occurrence table for Malawi IDSR data"
        },
        {
            "@type": "schema:Dataset",
            "name": "drug_exposure",
            "description": "OMOP CDM drug exposure table for Malawi IDSR data"
        },
        {
            "@type": "schema:Dataset",
            "name": "location",
            "description": "OMOP CDM location table for Malawi IDSR data"
        },
        {
            "@type": "schema:Dataset",
            "name": "measurement",
            "description": "OMOP CDM measurement table for Malawi IDSR data"
        }
      ]
    },
    {
      "@id": "concept:37311061",
      "@type": "schema:MedicalCondition",
      "code": {
        "@type": "schema:MedicalCode",
        "codeValue": "840539006",
        "codingSystem": "SNOMED",
        "sameAs": "http://snomed.info/id/840539006"
      },
      "identifier": "37311061",
      "name": "Disease caused by severe acute respiratory syndrome coronavirus 2"
    },
    {
      "@id": "concept:201820",
      "@type": "schema:MedicalRiskFactor",
      "increasesRiskOf": {
          "@type": "schema:MedicalCondition",
          "code": {
            "@type": "schema:MedicalCode",
            "codeValue": "840539006",
            "codingSystem": "SNOMED",
            "sameAs": "http://snomed.info/id/840539006"
          }
      },
      "code": {
        "@type": "schema:MedicalCode",
        "codeValue": "73211009",
        "codingSystem": "SNOMED",
        "sameAs": "http://snomed.info/id/73211009"
      },
      "identifier": "201820",
      "name": "Diabetes mellitus"
    },
    {
      "@id": "concept:317009",
      "@type": "schema:MedicalRiskFactor",
      "increasesRiskOf": {
          "@type": "schema:MedicalCondition",
          "code": {
            "@type": "schema:MedicalCode",
            "codeValue": "840539006",
            "codingSystem": "SNOMED",
            "sameAs": "http://snomed.info/id/840539006"
          }
      },
      "code": {
        "@type": "schema:MedicalCode",
        "codeValue": "195967001",
        "codingSystem": "SNOMED",
        "sameAs": "http://snomed.info/id/195967001"
      },
      "identifier": "317009",
      "name": "Asthma"
    },
    {
      "@id": "person:MuyingoS",
      "@type": "schema:Person",
      "schema:mainEntityOfPage": "<nil>",    
      "honorificSuffix": [
        "PhD"
      ],
      "jobTitle": [
        "Research Scientist"
      ],
      "name": "Sylvia Muyingo"
    },
    {
      "@id": "person:TaylorA",
      "@type": "schema:Person",
      "honorificSuffix": [
        "PhD"
      ],
      "jobTitle": [
        "Research Scientist"
      ],
      "name": "Amelia Taylor"
    },
    {
      "@id": "IDSRCovid19PrevalenceAndPredictionStudy/design",
      "@type": "schema:MedicalObservationalStudyDesign",
      "identifier": "<nil>",
      "url": "<nil>",
      "ohdsi:dateModified": "2020-03-28",
      "ohdsi:license": "open-source license",
      "ohdsi:designVersion": "5.4",
      "aphrc:protocol": [
          {
            "@type": "ohdsi:IncidenceRateAnalysis",
            "name": "<nil>",
            "description": "In an incidence calculation, we describe: amongst the persons in the target cohort, who experienced the outcome cohort during the time at risk period",
            "timeAtRisk":{
                "@type": "ohdsi:TimeAtRisk",
                "description": "The time at risk defines the time window relative to the target cohort start or end date in which a person is at risk to an outcome.",
                "startDate": "<nil>",
                "startDateOffset": "<nil>",
                "endDate": "<nil>",
                "endDateOffset": "<nil>"         
            },
            "url": "http://51.105.33.160:9090/Atlas/#/iranalysis/2",
            "ohdsi:targetCohort": 
                {
                  "@type": "schema:ItemList",
                  "name": "<nil>",
                  "url": "http://51.105.33.160:9090/Atlas/#/cohortdefinition/7",
                  "description": "Atlas webpage for Covid-19 patient cohort"
                },
            "ohdsi:outcomeCohort": 
                {
                  "@type": "schema:ItemList",
                  "name": "<nil>",
                  "url": "http://51.105.33.160:9090/Atlas/#/cohortdefinition/11",
                  "itemListElement": [
                      {
                        "@type": "schema:ListItem",
                        "identifier": "listItemEntryEvent",
                        "item": {
                            "@type": "schema:ItemList",
                            "identifier": "itemListEntryEventOccurrences",
                            "description": "This is an array of occurrences any one of which qualifies a person to move from the target cohort to the outcome cohort.",
                            "itemListElement": [
                                {
                                    "@type": "schema:MedicalEntity",
                                    "identifier": "medicalEntity #1",
                                    "code": {
                                        "@type": "schema:MedicalCode",
                                        "codeValue": "",
                                        "codingSystem": "SNOMED",
                                        "sameAs": "http://snomed.info/id/"
                                    },
                                    "guideline": {
                                        "@type": "schema:MedicalGuideline",
                                        "evidenceLevel": ["EvidenceLevelC"],
                                        "evidenceOrigin": "<nil>"
                                    }
                                },
                                {
                                   "@type": "schema:MedicalEntity",
                                    "identifier": "medicalEntity #n",
                                    "code": {
                                        "@type": "schema:MedicalCode",
                                        "codeValue": "",
                                        "codingSystem": "SNOMED",
                                        "sameAs": "http://snomed.info/id/"
                                    },
                                    "guideline": {
                                        "@type": "schema:MedicalGuideline",
                                        "evidenceLevel": ["EvidenceLevelC"],
                                        "evidenceOrigin": "<nil>"
                                    }
                                }
                            ]
                        },
                        "nextItem": "listItemInclusionCriteria",
                        "previousItem": "<nil>"
                      },
                      {
                        "@type": "ListItem",
                        "identifier": "listItemInclusionCriteria",
                        "description": "This is a placeholder for work in progress.",
                        "item": {"@type": "schema:ItemList"},
                        "nextItem": "listItemExitCriteria",
                        "previousItem": "listItemEntryEvent"
                      },
                      {
                        "@type": "ListItem",
                        "identifier": "listItemExitCriteria",
                        "description": "This is a placeholder for work in progress.",
                        "item": {"@type": "schema:ItemList"},
                        "nextItem": "<nil>",
                        "previousItem": "listItemMedicalTest"
                      }
                  ]
                },
            "ohdsi:stratifyCriteria": 
                {
                  "@type": "schema:ItemList",
                  "url": "http://51.105.33.160:9090/Atlas/#/iranalysis/2/definition",
                  "itemListElement": [
                      {
                        "@type": "schema:ListItem",
                        "item": {
                            "@type": "schema:MedicalIndication",
                            "description": "Age < 40",
                            "code": 
                            {
                                "@type": "schema:MedicalCode",
                                "codeValue": "<nil>",
                                "codingSystem": "<nil>",
                                "sameAs": "<nil>"
                            }
                        }
                      },
                      {
                        "@type": "schema:ListItem",
                        "item": {
                            "@type": "schema:MedicalIndication",
                            "description": "Age between 40 and 65",
                            "code": 
                            {
                                "@type": "schema:MedicalCode",
                                "codeValue": "<nil>",
                                "codingSystem": "<nil>",
                                "sameAs": "<nil>"
                            }
                        }
                      }, 
                      {
                        "@type": "schema:ListItem",
                        "item": {
                            "@type": "schema:MedicalIndication",
                            "description": "Age > 65",
                            "code": 
                            {
                                "@type": "schema:MedicalCode",
                                "codeValue": "<nil>",
                                "codingSystem": "<nil>",
                                "sameAs": "<nil>"
                            }
                        }
                      },
                      {
                        "@type": "schema:ListItem",
                        "item": {
                            "@type": "schema:MedicalIndication",
                            "description": "Pre-existing condition: asthma",
                            "code": 
                            {
                                "@type": "schema:MedicalCode",
                                "codeValue": "195967001",
                                "codingSystem": "SNOMED",
                                "sameAs": "http://snomed.info/id/195967001"
                            }
                        }
                      }, 
                      {
                        "@type": "schema:ListItem",
                        "item": {
                            "@type": "schema:MedicalIndication",
                            "description": "Pre-existing condition: diabetes",
                            "code": 
                            {
                                "@type": "schema:MedicalCode",
                                "codeValue": "195967001",
                                "codingSystem": "SNOMED",
                                "sameAs": "http://snomed.info/id/195967001"
                            }
                        }
                      }, 
                      {
                        "@type": "schema:ListItem",
                        "item": {
                            "@type": "schema:MedicalIndication",
                            "description": "The biological classification of individuals as female",
                            "code": 
                            {
                                "@type": "schema:MedicalCode",
                                "codeValue": "F",
                                "codingSystem": "OMOP Gender",
                                "sameAs": "https://athena.ohdsi.org/search-terms/terms/8532"
                            }
                        }
                      },
                      {
                        "@type": "schema:ListItem",
                        "item": {
                            "@type": "schema:MedicalIndication",
                            "description": "The biological classification of individuals as male",
                            "code": 
                            {
                                "@type": "schema:MedicalCode",
                                "codeValue": "M",
                                "codingSystem": "OMOP Gender",
                                "sameAs": "https://athena.ohdsi.org/search-terms/terms/8507"
                            }
                        }
                      },
                      {
                        "@type": "schema:ListItem",
                        "item": {
                            "@type": "schema:MedicalIndication",
                            "description": "Vaccinated for COVID",
                            "code": 
                            {
                                "@type": "schema:MedicalCode",
                                "codeValue": "85713-6",
                                "codingSystem": "LOINC",
                                "sameAs": "https://loinc.org/search/?t=1&s=85713-6"
                            }
                        }
                      }
                   ]
                }
          },
          {
            "@type": "ohdsi:PredictiveAnalysis",
            "name": "OHDSIPredictiveAnalysis",
            "description": "Predictive analysis uses supervised learning. A target cohort is defined. From the target an outcome cohort is selected based on one or more CDM occurrences (e.g. measurements and/or diagnoses and/or death). With these CDM outcome occurrences, their concepts serve as the labels. Next OHDSI tries to account for these labeled outcomes with predictors that are also extracted from the same target cohort. In OHDSI predictors automatically include demographics as well as perhaps specific occurrences the Principal Investigator (PI) chooses from the target cohort person/patient record. A PI also specifies one or more supervised learning algorithms each with their own hyper-parameter settings (e.g., regularized logistic regression, gradient boosting machines, random forest, K-nearest neighbors, Naïve Bayes, etc.). Finally, predictive analysis tries each of these algorithms to determine which one(s) provide the best fit between the predictors (independent variables and the labelled outcomes (dependent variables).",
            "disambiguatingDescription": "Predictive analysis in OHDSI uses the same interface called ATLAS used in descriptive and causal analysis. Using ATLAS, a supervised learning experiment can be specified and executed codelessly. In the process ATLAS orchestrates a set of R packages that a user can orchestrate directly in the event specialization is needed. For example, as in attention-based learning, there may be a need that is not empirical to weigh certain predictors and outcomes more than others.",
            "ohdsi:targetCohort": {
              "@type": "schema:ItemList",
              "name": "TargetCohortDefinition"
            },
            "ohdsi:outcomeCohort": {
              "@type": "schema:ItemList",
              "name": "OutcomeCohortDefinition"
            },
            "ohdsi:analysisModel": {
              "@type": "schema:SoftwareApplication",
              "name": "HADES (Health Analytics Data-To-Evidence Suite)",
              "description": "HADES (formally known as the OHDSI Methods Library) is a set of open source R packages for large scale analytics, including population characterization, population-level causal effect estimation, and patient-level predictiction.",
              "url": "https://ohdsi.github.io/Hades/",
              "applicationCategory": "Health Analytics",
              "downloadUrl": "https://github.com/OHDSI/Hades",
              "featureList": "One feature of HADES is that includes a package of prediction analysis methods that it exercises in determining a best method for prediction with a target cohort and and outcomes cohort and a set of predictors.",
              "softwareHelp": {
                  "@type": "schema:CreativeWork",
                  "name": "The Book of OHDSI: Chapter 13",
                  "url": "https://ohdsi.github.io/TheBookOfOhdsi/PatientLevelPrediction.html"
              },
              "aphrc:analysisModelDetails": {
                  "@type": "schema:ItemList",
                  "name": "AnalysisModelDetails",
                  "description": "This is a placeholder for work in progress. The scope of this ItemList are patient level prediction settings in ATLAS.",
                   "itemListElement": [
                      {
                        "@type": "schema:ItemList",
                        "name": "ModelSettings (from ohdsi:ATLAS)",
                        "description": "To add a supervised learning algorithm click on the “Add Model Settings” button. A dropdown containing all the models currently supported in the ATLAS interface will appear. We can select the supervised learning model we want to include in the study by clicking on the name in the dropdown menu. This will then show a view for that specific model, allowing the selection of the hyper-parameter values. If multiple values are provided, a grid search is performed across all possible combinations of values to select the optimal combination using cross-validation."
                      },
                      {
                        "@type": "schema:ItemList",
                        "name": "CovariateSettings (from ohdsi:ATLAS)",
                        "description": "We have defined a set of standard covariates that can be extracted from the observational data in the CDM format. In the covariate settings view, it is possible to select which of the standard covariates to include. We can define different types of covariate settings, and each model will be created separately with each specified covariate setting."
                      },
                      {
                        "@type": "schema:ItemList",
                        "name": "PopulationSettings (from ohdsi:ATLAS)",
                        "description": "The population settings is where addition inclusion criteria can be applied to the target population and is also where the time-at-risk is defined. "
                      }
                  ]
              }
            }
         }   
      ]
    },
    {
      "@id": "study:IDSRCovid19PrevalenceAndPredictionStudy",
      "@type": "schema:MedicalObservationalStudy",
      "identifier": "<nil>",
      "name": "Prevalence and Prediction of COVID-19 By Subgroup across several SSA countries: a Network Study",
      "description": "The objective of this study is to predict and provide incident rates by subgroups for COVID-19 using the WHO Integrated Disease Surveillance and Response (IDSR) person-level CRF used as adopted by many countries across Subsaharan Africa",
      "image": "https://lucid.app/documents/view/10790453-aed5-4f7c-906e-caa414531987",
      "url": "https://aphrc.org/inspire/",
      "studyLocation": [
         {
             "@type": "Country",
             "name": "Malawi"
         },
         {
             "@type": "Country",
             "name": "Kenya"
         },
         {
             "@type": "Country",
             "name": "Uganda"
         }
      ],
      "ohdsi:studyType": ["ohdsi:PopulationHealthApplication"],
      "ohdsi:medicalStudyUseCase": [
        ["ohdsi:Characterization"], ["ohdsi:PatientLevelPrediction"]
      ],
      "mainEntityOfPage": "<nil>",
      "studyDesign": "IDSRCovid19PrevalenceAndPredictionStudy/design",
      "status": ["ohdsi:ResultsAvailable"],
      "healthCondition": [
        "concept:37311061"
      ],
      "studySubject": [
        "concept:201820",
        "concept:317009"
      ],
      "subjectOf": [
          "creativework:IDSRproject"
      ],
      "potentialAction": [
        {
          "@type": "schema:UpdateAction",
          "name": "MedicalObservationalStudy Execute Action",
          "agent": [
            "person:MuyingoS"
          ],
          "instrument": {
              "@type": "schema:ItemList",
              "name": "OHDSI R library",
              "description": "The software stack by way of which the Action produces the Result from the Object dataset(s) at the Target",
              "itemListElement": [
              {
                "@type": "schema:ListItem",
                "name": "ATLAS",
                "item": {
                    "@type": "schema:SoftwareApplication",
                    "softwareVersion": "2.13",
                    "applicationCategory": "R Package",
                    "description": "ATLAS is an open source software tool for researchers to conduct scientific analyses on standardized observational data converted to the OMOP Common Data Model V5. Researchers can create cohorts by defining groups of people based on an exposure to a drug or diagnosis of a particular condition using healthcare claims data. ATLAS has vocabulary searching of medical concepts to identify people with specific conditions, drug exposures etc. Patient profiles can be viewed within a specific cohort allowing visualization of a particular subject's health care records. Population effect level estimation analyses allows for comparison of two different cohorts and leverages R packages."
                  }
              },
              {
                "@type": "schema:ListItem",
                "name": "ACHILLES",
                "item": {
                    "@type": "schema:SoftwareApplication",
                    "softwareVersion": "1.7",
                    "applicationCategory": "R Package",
                    "description": "Automated Characterization of Health Information at Large-scale Longitudinal Evidence Systems (ACHILLES). Achilles provides descriptive statistics on an OMOP CDM database. ACHILLES currently supports CDM version 5.3 and 5.4."
                }
              },
              {
                "@type": "schema:ListItem",
                "name": "HADES",
                "item": {
                    "@type": "schema:SoftwareApplication",
                    "softwareVersion": "5.0.3",
                    "applicationCategory": "R Package",
                    "description": "HADES includes PatientLevelPrediction. PatientLevelPrediction is an R package for building and validating patient-level predictive models using data in the OMOP Common Data Model format."
                }
              },
              {
                "@type": "schema:ListItem",
                "name": "WebAPI",
                "item": {
                    "@type": "schema:SoftwareApplication",
                    "softwareVersion": "2.13",
                    "applicationCategory": "R Package",
                    "description": "OHDSI WebAPI contains all OHDSI RESTful services that can be called from OHDSI applications."
                }
              }
            ]
          },
          "target": [
            "http://51.105.33.160:9090/Atlas",
             {
               "@type": "EntryPoint",
               "actionPlatform": "ATLAS",
               "description": "ATLAS is an open source software tool for researchers to conduct scientific analyses on standardized observational data converted to the OMOP Common Data Model V5. Researchers can create cohorts by defining groups of people based on an exposure to a drug or diagnosis of a particular condition using healthcare claims data. ATLAS has vocabulary searching of medical concepts to identify people with specific conditions, drug exposures etc. Patient profiles can be viewed within a specific cohort allowing visualization of a particular subject's health care records. Population effect level estimation analyses allows for comparison of two different cohorts and leverages R packages.",
               "urlTemplate": "http://51.105.33.160:9090/Atlas",
               "contentType": "text/plain"
             }
          ],
          "object": [
              "dataset:mubasCDM",
              "dataset:coordinatingcenterCDM"
          ],
          
          "result": {
              "@type": "schema:ItemList",
              "name": "OHDSIStudyPackageResultsSchema",
              "description": "Hosts study settings (metadata) and study results (aggregate data) by analysis from the study package",
              "itemListElement": [
              {
                "@type": "schema:ListItem",
                "name": "OHDSIStudyPackageMetadata",
                "item": {
                    "@type": "schema:ItemList",
                    "name": "MachineActionableSettingByAnalysis",
                    "description": "OHDSI study package metadata by analysis. Facilitates sharing of analysis settings across multiple CDMs at different institutions"
                }
              },
              {
                "@type": "schema:ListItem",
                "name": "OHDSIStudyPackageAggregateData",
                "item": {
                    "@type": "schema:ItemList",
                    "name": "IndicatorCollections",
                    "description": "OHDSI study package aggregate study data by analysis formatted for synthesis at a network study coordinating center",
                    "subjectOf": [{
                        "@type": "schema:CreativeWork",
                        "name": "EvidenceSynthesis",
                        "description": "This R package contains routines for combining causal effect estimates and study diagnostics across multiple data sites in a distributed study. This includes functions for performing meta-analysis and forest plots.",
                        "disambiguatingDescription": "Not for use in synthesizing predictive analysis network studies across CDMs. Achieving transportability of predictive analysis models takes techniques like transfer learning, attention based learning and/or fine turning.",
                        "url": "https://ohdsi.github.io/EvidenceSynthesis/"
                    }]
                }
              }
            ]
          },
          "actionStatus": ["PotentialActionStatus"]
        },
        {
            "@type": "schema:updateAction",
            "name": "MedicalObservationalStudy CDM ETL Action",
            "result": [
                "dataset:mubasCDM"
            ],
            "object": {
                "@type": "schema:Dataset",
                "name": "Case-based Surveillance Reporting Form",
                "maintainer": "Malawi Ministry of Health",
                "schemaVersion": "4.2.1 2021",
                "isBasedOn": {
                    "@type": "schema:CreativeWork",
                    "creator": {
                        "@type": "schema:Organization",
                        "legalName": "World Health Organization"
                    },
                    "name": "IDSR immediate case-based reporting form (Appendix 2F)",
                    "url": "https://apps.who.int/iris/bitstream/handle/10665/312317/WHO-AF-WHE-CPI-01-2019-eng.pdf"
                }
            },
            "instrument": {
                "@type": "schema:SoftwareSourceCode",
                "codeRepository": "<nil>",
                "programmingLanguage": "SQL",
                "runtimePlatform": "<nil>",
                "isBasedOn": {
                    "@type": "schema:SoftwareApplication",
                    "name": "Rabbit in a Hat",
                    "url": "https://ohdsi.github.io/WhiteRabbit/RabbitInAHat.html"
                }
            }
          }
      ]
    }
  ]
}